fulfill-0.0.1.dist-info/METADATA
fulfill-0.0.1.dist-info/WHEEL
fulfill-0.0.1.dist-info/entry_points.txt
fulfill-0.0.1.dist-info/licenses/LICENSE
fulfill/__init__.py
fulfill/__main__.py
fulfill/cli.py
fulfill/debug.py
fulfill/py.typed
fulfill-0.0.1.dist-info/RECORD
