Metadata-Version: 2.1
Name: fulfill
Version: 0.0.1
Summary: Manage your project. Fulfill your duties.
Author-Email: =?utf-8?q?Timoth=C3=A9e_Mazzucotelli?= <dev@pawamoy.fr>
License: ISC
Classifier: Development Status :: 3 - Alpha
Classifier: Intended Audience :: Developers
Classifier: Programming Language :: Python
Classifier: Programming Language :: Python :: 3
Classifier: Programming Language :: Python :: 3 :: Only
Classifier: Programming Language :: Python :: 3.8
Classifier: Programming Language :: Python :: 3.9
Classifier: Programming Language :: Python :: 3.10
Classifier: Programming Language :: Python :: 3.11
Classifier: Programming Language :: Python :: 3.12
Classifier: Programming Language :: Python :: 3.13
Classifier: Topic :: Software Development
Classifier: Topic :: Utilities
Classifier: Typing :: Typed
Project-URL: Homepage, https://pawamoy.github.io/fulfill
Project-URL: Documentation, https://pawamoy.github.io/fulfill
Project-URL: Changelog, https://pawamoy.github.io/fulfill/changelog
Project-URL: Repository, https://github.com/pawamoy/fulfill
Project-URL: Issues, https://github.com/pawamoy/fulfill/issues
Project-URL: Discussions, https://github.com/pawamoy/fulfill/discussions
Project-URL: Gitter, https://gitter.im/fulfill/community
Project-URL: Funding, https://github.com/sponsors/pawamoy
Requires-Python: >=3.8
